notion_requests/__init__.py
notion_requests/client.py
notion_requests/version.py
notion_requests-0.1.1.dist-info/LICENSE
notion_requests-0.1.1.dist-info/METADATA
notion_requests-0.1.1.dist-info/WHEEL
notion_requests-0.1.1.dist-info/top_level.txt
notion_requests-0.1.1.dist-info/RECORD
