Metadata-Version: 2.1
Name: notion-requests
Version: 0.1.1
Summary: Notion Python SDK Client using Requests.
Home-page: https://github.com/nyoungstudios/notion-py-requests
Author: Nathaniel Young
Author-email: 
Maintainer: Nathaniel Young
Maintainer-email: 
License: MIT
Keywords: notion api client sdk python
Platform: UNKNOWN
Classifier: Development Status :: 4 - Beta
Classifier: Intended Audience :: Developers
Classifier: License :: OSI Approved :: MIT License
Classifier: Operating System :: OS Independent
Classifier: Programming Language :: Python :: 3.6
Classifier: Programming Language :: Python :: 3.7
Classifier: Programming Language :: Python :: 3.8
Classifier: Programming Language :: Python :: 3.9
Classifier: Topic :: Utilities
Requires-Python: >=3.6,<4.0
License-File: LICENSE
Requires-Dist: requests
